{
  "relationships": [
    {
      "id": "e4531c9a-49a5-5cff-9710-5a010416b43e",
      "source_concept_id": "c9ac7584-d5cd-4b19-9caa-8ecb948cf35f",
      "target_concept_id": "f3aa8ea8-bbd6-40ba-93a3-64751b6e60fb",
      "type": "uses",
      "confidence": 0.666,
      "evidence": "me to test: Open veno versus iGPU versus, uh, stable diffusion or NPU whatever. Just just wr",
      "detection_method": "pattern_matching",
      "source_video_id": "1Hp5Z2QDsKw",
      "source_group_id": 4,
      "target_video_id": "1Hp5Z2QDsKw",
      "target_group_id": 4,
      "temporal_distance": 0.0,
      "extracted_at": "2025-10-10T00:06:35.288251"
    },
    {
      "id": "6a02b104-06f8-508a-a915-2251f004aa47",
      "source_concept_id": "f3aa8ea8-bbd6-40ba-93a3-64751b6e60fb",
      "target_concept_id": "c9ac7584-d5cd-4b19-9caa-8ecb948cf35f",
      "type": "uses",
      "confidence": 0.666,
      "evidence": "me to test: Open veno versus iGPU versus, uh, stable diffusion or NPU whatever. Just just wr",
      "detection_method": "pattern_matching",
      "source_video_id": "1Hp5Z2QDsKw",
      "source_group_id": 4,
      "target_video_id": "1Hp5Z2QDsKw",
      "target_group_id": 4,
      "temporal_distance": 0.0,
      "extracted_at": "2025-10-10T00:06:35.291322"
    }
  ],
  "metadata": {
    "total_relationships": 2,
    "video_ids": [
      "1Hp5Z2QDsKw"
    ],
    "avg_confidence": 0.666,
    "type_distribution": {
      "uses": 2
    },
    "detection_method_distribution": {
      "pattern_matching": 2
    },
    "extraction_time": "2025-10-10T00:06:35.399887"
  }
}